xrpld_publisher/__init__
xrpld_publisher/models.py
xrpld_publisher/publisher.py
xrpld_publisher/utils.py
xrpld_publisher/validator.py
xrpld_publisher-2.0.2.dist-info/METADATA
xrpld_publisher-2.0.2.dist-info/WHEEL
xrpld_publisher-2.0.2.dist-info/RECORD
