Metadata-Version: 2.1
Name: xrpld-publisher
Version: 2.0.2
Summary: Xrpld validator lists publisher library
Author: Denis Angell
Author-email: dangell@transia.co
Requires-Python: >=3.9.6,<4.0.0
Classifier: Programming Language :: Python :: 3
Classifier: Programming Language :: Python :: 3.10
Classifier: Programming Language :: Python :: 3.11
Requires-Dist: PyYAML (>=6.0,<7.0)
Requires-Dist: cryptography (>=41.0.7,<42.0.0)
Requires-Dist: pytest (>=7.2.1,<8.0.0)
Requires-Dist: python-dotenv (>=1.0.0,<2.0.0)
Requires-Dist: requests (>=2.31.0,<3.0.0)
Requires-Dist: xrpl-py (>=2.4.0,<3.0.0)
